wirebind/__init__.py
wirebind/binds/__init__.py
wirebind/binds/atom.py
wirebind/broadcast.py
wirebind/demo.py
wirebind/encoding.py
wirebind/main.py
wirebind/message.py
wirebind/multiplex.py
wirebind/rpc.py
wirebind/sender.py
wirebind-0.0.1.dist-info/METADATA
wirebind-0.0.1.dist-info/WHEEL
wirebind-0.0.1.dist-info/entry_points.txt
wirebind-0.0.1.dist-info/RECORD
