Metadata-Version: 2.1
Name: wirebind
Version: 0.0.1
Summary: A networking library for distributed applications
License: MIT
Author: Paul Butler
Author-email: paul@driftingin.space
Requires-Python: >=3.9,<4.0
Classifier: License :: OSI Approved :: MIT License
Classifier: Programming Language :: Python :: 3
Classifier: Programming Language :: Python :: 3.9
Classifier: Programming Language :: Python :: 3.10
Classifier: Programming Language :: Python :: 3.11
Requires-Dist: cbor2 (>=5.4.6,<6.0.0)
Requires-Dist: websockets (>=11.0.2,<12.0.0)
